nekobin/__init__.py
nekobin/main.py
pyNekobin-3.1.dist-info/LICENSE
pyNekobin-3.1.dist-info/METADATA
pyNekobin-3.1.dist-info/WHEEL
pyNekobin-3.1.dist-info/top_level.txt
pyNekobin-3.1.dist-info/RECORD
