Metadata-Version: 2.1
Name: pyNekobin
Version: 3.1
Summary: Paste codes to Nekobin.com with python
Home-page: https://github.com/Nusab19/pyNekobin
Download-URL: https://github.com/Nusab19/pyNekobin/releases/tag/pyNekobin-3.1
Author: Nusab Taha
Author-email: nusabtaha33@gmail.com
License: MIT
Keywords: Nekobin,pyNekobin,Paste Code,Paste Bin
Classifier: License :: OSI Approved :: MIT License
Classifier: Operating System :: OS Independent
Classifier: Programming Language :: Python
Classifier: Programming Language :: Python :: 3
Classifier: Programming Language :: Python :: 3.6
Classifier: Programming Language :: Python :: 3.7
Classifier: Programming Language :: Python :: 3.8
Classifier: Programming Language :: Python :: 3.9
Classifier: Programming Language :: Python :: 3.10
Classifier: Programming Language :: Python :: 3.11
License-File: LICENSE
Requires-Dist: httpx
